inventree_order_history-0.7.1.dist-info/licenses/LICENSE
order_history/__init__.py
order_history/core.py
order_history/helpers.py
order_history/serializers.py
order_history/version.py
order_history/views.py
order_history/static/OrderHistoryPanel.js
inventree_order_history-0.7.1.dist-info/METADATA
inventree_order_history-0.7.1.dist-info/WHEEL
inventree_order_history-0.7.1.dist-info/entry_points.txt
inventree_order_history-0.7.1.dist-info/top_level.txt
inventree_order_history-0.7.1.dist-info/RECORD
